{
  "url": "https://www.facebook.com/permalink.php?story_fbid=pfbid02XA7bmaZ8GbkyhB7c4GUnRRA8TZRmLoph9PHu4cBWCgGdWfXEg3aJfoMFyCGevysFl&id=100064853043607",
  "comments": [
    {
      "name": "Savinica Ionascu 20 minutes",
      "text": "Tot Nicușor Dan i-a scos din minti pe cotracanditatii din sala!\nAsa aroganta pe care ne-a arătat o Nicușor, doar la Iohanis am mai văzut!\nAuzi la el, ii spune lui Funeriu ca el este IRELEVANT,contează doar patru candidați, el Nicușor, Simion, Antonescu… See more"
    },
    {
      "name": "Irina Barjoveanu-vladu a week",
      "text": "Adevărat a înviat! Azi, în prima zi de Paști, ați fost la înălțime, că de obicei, în lupta cu incendiile de vegetație uscată. Ați lichidat un incendiu pe o suprafață mare de pășune, ce amenință pădurea, la 9 km de Anina. Respect. Dar am văzut acum, la … See more"
    },
    {
      "name": "Carina Nichifor a week",
      "text": "Adevărat a înviat!"
    },
    {
      "name": "Elly Elly a week",
      "text": "Adevărat a înviat!"
    },
    {
      "name": "Letiția Dobre a week",
      "text": "Adevărat a înviat"
    },
    {
      "name": "Caracas Marita a week",
      "text": "Adevărat a înviat!"
    },
    {
      "name": "Gyongyike Armas a week",
      "text": "Adevărat a înviat !"
    },
    {
      "name": "Georgian Brundean a week",
      "text": "Adevărat a înviat!"
    },
    {
      "name": "Alyn Golet a week",
      "text": "Adevărat a înviat!"
    },
    {
      "name": "Mioara Ponoran a week",
      "text": "Adevărat a înviat!"
    },
    {
      "name": "Tantza Tantza a week",
      "text": "Adevărat a înviat!!!"
    },
    {
      "name": "Cosmina Medoia a week",
      "text": "Adevărat a înviat!"
    },
    {
      "name": "Crepelca Dana Si Iarci a week",
      "text": "Adevărat a înviat!"
    },
    {
      "name": "Ana Serbanoiu a week",
      "text": "Sărbători binecuvântate!"
    },
    {
      "name": "Valeria Valeria Ciornei a week",
      "text": "Adevărat a înviat !"
    },
    {
      "name": "Elena Lucia a week",
      "text": "Adevărat a Înviat!"
    },
    {
      "name": "Ilie Laitin a week",
      "text": "Adevărat a înviat!"
    },
    {
      "name": "Gherlinde Stan a week",
      "text": "Adevărat a înviat!"
    },
    {
      "name": "Alina Curiac a week",
      "text": "Adevărat a înviat!"
    },
    {
      "name": "Oly Olimpia a week",
      "text": "Adevarat a Înviat!"
    },
    {
      "name": "Claudia Gaspar a week",
      "text": "Adevărat a înviat!"
    },
    {
      "name": "Nikoleta Dusu a week",
      "text": "Adevărat a înviat!!"
    },
    {
      "name": "Mirela Vaszi a week",
      "text": "Adevărat a înviat"
    },
    {
      "name": "Florica Lucia Marie a week",
      "text": "Adevărat a înviat! Paște fericit vă doresc și eu!"
    },
    {
      "name": "Daniela Manea a week",
      "text": "Adevărat a Înviat!"
    },
    {
      "name": "Marius Belu a week",
      "text": "Adevărat a înviat!"
    },
    {
      "name": "Luminița Dragomir a week",
      "text": "Adevărat a înviat"
    },
    {
      "name": "Vasilica Tatucu a week",
      "text": "Adevarat a inviat!"
    },
    {
      "name": "Estera Camelia a week",
      "text": "Adevărat a înviat!"
    },
    {
      "name": "Daniela Botea a week",
      "text": "Adevărat a înviat !"
    },
    {
      "name": "Petrisor Rudila a week",
      "text": "Adevărat a înviat...!Sărbători Pascale cu sanatate si Binecuvântări de la Bunul Dumnezeu...!"
    },
    {
      "name": "Oprea Camelia a week",
      "text": "Adevărat a Înviat!"
    },
    {
      "name": "Maria Bikasz a week",
      "text": "Adevărat a Înviat Și Un Paște Fericit !"
    },
    {
      "name": "Marioara Ciurel a week",
      "text": "Adevarat a inviat!"
    },
    {
      "name": "Mihoc Alexandru a week",
      "text": "Adevărat a înviat."
    },
    {
      "name": "Ginomario Craciun a week",
      "text": "Adevărat a Inviat"
    },
    {
      "name": "Voichita Pilug a week",
      "text": "Adevărat a înviat !"
    },
    {
      "name": "Romina Maria Popescu a week",
      "text": "Asemenea vă doresc."
    },
    {
      "name": "Zepa Letitia Mariana a week",
      "text": "Adevărat a Înviat!"
    },
    {
      "name": "Dina Agape a week",
      "text": "Adevărat a înviat!"
    },
    {
      "name": "Gianina Fabian a week",
      "text": "Adevărat a înviat!"
    },
    {
      "name": "Matyas Romeo a week",
      "text": "Dumnezeu să vă Binecuvânteze!"
    },
    {
      "name": "Eugeni Cazan a week",
      "text": "Adevarat a inviat!"
    },
    {
      "name": "Nicolae Rotariu a week",
      "text": "Adevarat a inviat!"
    },
    {
      "name": "Dana Berzescu a week",
      "text": "Adevărat a înviat!"
    },
    {
      "name": "Daniel Ghiocel a week",
      "text": "Adevarat a inviat!"
    },
    {
      "name": "Kyky Cristina a week",
      "text": "Adevărat a înviat"
    },
    {
      "name": "Belea Gabriel a week",
      "text": "Adevărat a Înviat"
    },
    {
      "name": "Rosemarie Boden a week",
      "text": "Adevarat a inviat"
    },
    {
      "name": "Lazarica Gaina a week",
      "text": "Adevărat a înviat!"
    },
    {
      "name": "Gheorghe Ghiță Mergia a week",
      "text": "Adevărat a înviat!"
    },
    {
      "name": "Florica Beloia a week",
      "text": "Adevărat a înviat"
    },
    {
      "name": "Maria Brabete a week",
      "text": "Adevărat a înviat!"
    },
    {
      "name": "Ion Bumbescu a week",
      "text": "Adevărat a înviat"
    },
    {
      "name": "Simona Nisic a week",
      "text": "Adevărat a înviat"
    },
    {
      "name": "Neacsu Maria Ex Brinzei a week",
      "text": "Adevărat a înviat!"
    },
    {
      "name": "Homicianu Elena a week",
      "text": "Adevărat a înviat!"
    },
    {
      "name": "Izabella-andreea Florescu a week",
      "text": "Sărbători Pascale pline de binecuvântări!"
    },
    {
      "name": "Luminita Baraghin a week",
      "text": "Adevarat a inviat."
    },
    {
      "name": "Irina Murariu a week",
      "text": "Adevarat a inviat!"
    },
    {
      "name": "Maria Elena Dulcă a week",
      "text": "Adevărat a înviat!Paște liniștit!"
    },
    {
      "name": "Omerca Tripa a week",
      "text": "Adevărat a înviat!!!"
    },
    {
      "name": "Camelya Marya a week",
      "text": "Adevărat a înviat!"
    },
    {
      "name": "Dorel Hadade a week",
      "text": "Adevărat a înviat!"
    },
    {
      "name": "Angela Ardelean a week",
      "text": "Adevărat a înviat!"
    },
    {
      "name": "Jian Sorypaula a week",
      "text": "Adevărat a Înviat!"
    },
    {
      "name": "Damian Silvia a week",
      "text": "Adevărat a înviat"
    },
    {
      "name": "Manea Marilena a week",
      "text": "Adevărat a înviat!"
    },
    {
      "name": "Elena Denisa Ella a week",
      "text": "Adevărat a Înviat!"
    },
    {
      "name": "Flori Floare Floare a week",
      "text": "Adevărat a înviat"
    },
    {
      "name": "Adriana Adry a week",
      "text": "Adevărat a înviat!"
    },
    {
      "name": "Monica Constantin a week",
      "text": "Adevărat a înviat!"
    },
    {
      "name": "Doina Tolea 5 days",
      "text": "Respect salvatorilor!"
    },
    {
      "name": "Balici Ilie-petrica a week",
      "text": "Adevărat a înviat"
    },
    {
      "name": "Manuela Popirlan a week",
      "text": "Adevărat a înviat"
    },
    {
      "name": "Mihaela Tica a week",
      "text": "Adevărat a înviat și Paște fericit cu sănătate, vă doresc să aveți !"
    },
    {
      "name": "Nicoleta Itaru a week",
      "text": "Adevarat a inviat!"
    },
    {
      "name": "Nagy Alexandru a week",
      "text": "Adevărat a înviat!"
    },
    {
      "name": "Marius Burlacu a week",
      "text": "Adevărat a înviat!"
    },
    {
      "name": "Robert Vâlcu a week",
      "text": "Adevărat a înviat!"
    },
    {
      "name": "Ilie Georgeta a week",
      "text": "Adevărat a înviat"
    },
    {
      "name": "Simion Fiat a week",
      "text": "PAȘTE FERICIT"
    },
    {
      "name": "Adriana Sculici a week",
      "text": "ADEVĂRAT A ÎNVIAT"
    },
    {
      "name": "Prundeanu Valeriu a week",
      "text": "Adevarat a inviat!"
    },
    {
      "name": "Andreea Nistor a week",
      "text": "Adevărat a înviat"
    },
    {
      "name": "Romanu Felicia a week",
      "text": "Adevărat a înviat! Paște fericit isu Caraș Severin!"
    },
    {
      "name": "Marinela Preda a week",
      "text": "Adevärat a Inviat!"
    },
    {
      "name": "Florentina Maria Redica a week",
      "text": "Adevărat a înviat paste fericit"
    },
    {
      "name": "Sonia-Lorena Panescu a week",
      "text": "Adevărat a înviat! Paste fericit!"
    },
    {
      "name": "Alina Citu a week",
      "text": "Adevarat a înviat!Paste fericit!"
    },
    {
      "name": "Eana Victoria a week",
      "text": "Adevărat a înviat. Paște fericit"
    },
    {
      "name": "Olimpia Mihai Donea a week",
      "text": "Adevarat a inviat! Paste binecuvintat!"
    },
    {
      "name": "Nico Dragota a week",
      "text": "Adevărat a înviat! Sărbători frumoase"
    },
    {
      "name": "Kristina Crisan a week",
      "text": "Adevarat a inviat !Sarbatori binecuvantate !"
    },
    {
      "name": "Martin Daniela a week",
      "text": "Adevărat a înviat ! Sărbători binecuvântate !"
    },
    {
      "name": "Lia Papafil a week",
      "text": "Adevărat a înviat!"
    },
    {
      "name": "Martin Elena Gabriela a week",
      "text": "Adevărat a înviat.\nSărbători binecuvântate ."
    },
    {
      "name": "Mario H. Balint a week",
      "text": "Adevărat a înviat!"
    },
    {
      "name": "Rori Nicola a week",
      "text": "Adevărat a înviat Paște binecuvântat"
    },
    {
      "name": "Cristina Nicu Orbu a week",
      "text": "Adevărat a înviat! Paște binecuvântat ISU Caraș Severin!"
    },
    {
      "name": "Ioana Micláu a week",
      "text": "Adevărat a înviat\nPaște binecuvintat"
    }
  ],
  "message": "Hristos a înviat!"
}