{
  "transparencyStatus": "Clicked",
  "seeMoreStatus": "Not found (timeout)",
  "historyEntries": [
    "Changed name to Andra Măruță\nMay 14, 2017",
    "Changed name to Iubim Crăciunul\nMarch 3, 2017",
    "Created - Johny Bravo Romania.\nMarch 8, 2014"
  ],
  "adsStatus": [
    "This Page is not currently running ads."
  ],
  "pageManagers": [
    "Primary country/region location for people who manage this Page includes:",
    "Romania (4)"
  ],
  "url": "https://www.facebook.com/fanpageandra2",
  "date": "2025-04-30"
}