{
  "transparencyStatus": "Clicked",
  "seeMoreStatus": "Not found (timeout)",
  "historyEntries": [
    "Created - Fraiere, eu te iubesc.\nAugust 31, 2012"
  ],
  "adsStatus": [
    "This Page is not currently running ads.",
    "This Page has run ads about social issues, elections or politics."
  ],
  "pageManagers": [
    "Primary country/region location for people who manage this Page includes:",
    "Romania (2)"
  ],
  "url": "https://www.facebook.com/FraiereEuTeIubesc",
  "date": "2025-04-30"
}